logit_python/__init__.py
logit_python/base_logger.py
logit_python/db_logger.py
logit_python/default_logger.py
logit_python/multi_logger.py
logit_python/conf/__init__.py
logit_python/conf/logit_conf.py
logit_python/conf/logit_db_conf.py
logit_python/conf/logit_multi_conf.py
logit_python-1.0.1.dist-info/METADATA
logit_python-1.0.1.dist-info/WHEEL
logit_python-1.0.1.dist-info/top_level.txt
logit_python-1.0.1.dist-info/RECORD
